cpge/graph/__init__.py
cpge/graph/anim.py
cpge/graph/draw.py
cpge/graph/generate.py
cpge-1.0.1.dist-info/WHEEL
cpge-1.0.1.dist-info/METADATA
cpge-1.0.1.dist-info/RECORD
